quanfluence_sdk/__init__.py
quanfluence_sdk/quanfluence_client.py
quanfluence_sdk/version.py
quanfluence_sdk-0.0.6.dist-info/licenses/LICENSE
quanfluence_sdk-0.0.6.dist-info/METADATA
quanfluence_sdk-0.0.6.dist-info/WHEEL
quanfluence_sdk-0.0.6.dist-info/top_level.txt
quanfluence_sdk-0.0.6.dist-info/RECORD
