Metadata-Version: 2.4
Name: quanfluence_sdk
Version: 0.0.6
Summary: Quanfluence Developer Kit for Python
Home-page: https://github.com/quanfluence/python-quanfluence-sdk
Download-URL: https://github.com/quanfluence/python-quanfluence-sdk/archive/v_01.tar.gz
Author: Quanfluence SDK
Author-email: sdk@quanfluence.com
License: MIT
Keywords: quanfluence,quanfluence-api,web-api,sdk,rest-api-client
Classifier: Development Status :: 3 - Alpha
Classifier: Intended Audience :: Developers
Classifier: Topic :: Software Development :: Build Tools
Classifier: Operating System :: OS Independent
Classifier: License :: OSI Approved :: MIT License
Classifier: Programming Language :: Python :: 3
Classifier: Programming Language :: Python :: 3.6
Classifier: Programming Language :: Python :: 3.7
Classifier: Programming Language :: Python :: 3.8
Classifier: Programming Language :: Python :: 3.9
Classifier: Programming Language :: Python :: 3.10
Classifier: Programming Language :: Python :: 3.11
Requires-Python: >=3.6.0
License-File: LICENSE
Requires-Dist: requests>=2.23.0
Dynamic: author
Dynamic: author-email
Dynamic: classifier
Dynamic: description
Dynamic: description-content-type
Dynamic: download-url
Dynamic: home-page
Dynamic: keywords
Dynamic: license
Dynamic: license-file
Dynamic: requires-dist
Dynamic: requires-python
Dynamic: summary
